jopilot_api/__init__.py
jopilot_api/job_search.py
jopilot_api-0.1.3.dist-info/METADATA
jopilot_api-0.1.3.dist-info/WHEEL
jopilot_api-0.1.3.dist-info/top_level.txt
jopilot_api-0.1.3.dist-info/RECORD
