Metadata-Version: 2.2
Name: jopilot-api
Version: 0.1.3
Summary: Python wrapper for the JoPilot API.
Home-page: https://jopilot.net/
Author: JoPilot
Author-email: developers@jopilot.net
Project-URL: Homepage, https://jopilot.net/
Project-URL: Documentation, https://api.jopilot.net/swagger/index.html
Project-URL: Source Code, https://github.com/jopilot-net/JoPilotAPI-python
Project-URL: Bug Tracker, https://github.com/jopilot-net/JoPilotAPI-python/issues
Classifier: Programming Language :: Python :: 3
Classifier: License :: OSI Approved :: MIT License
Classifier: Operating System :: OS Independent
Requires-Python: >=3.6
Requires-Dist: requests>=2.28.0
Dynamic: author
Dynamic: author-email
Dynamic: classifier
Dynamic: description
Dynamic: description-content-type
Dynamic: home-page
Dynamic: project-url
Dynamic: requires-dist
Dynamic: requires-python
Dynamic: summary
